{
  "generated_at": "2026-06-08T10:00:04+09:00",
  "source_file": "포트폴리오.xlsx",
  "method_note": "자산총계 시트 8행 이후 데이터를 기준으로 Python에서 평가금액과 비중을 직접 재계산했습니다. openpyxl 저장 후 수식 캐시가 사라지는 문제를 보완하기 위해 현금·예금의 단순 수식은 Python에서 보조 계산합니다. 장기예금은 투자기준 금액에서 제외했습니다.",
  "fx": {
    "usd_krw_sell_rate": 1546.81,
    "jpy_100_krw_sell_rate": 962.13,
    "jpy_1_krw_sell_rate": 9.6213
  },
  "totals": {
    "total_asset_krw": 223929220.0,
    "excluded_from_investment_base_krw": 27200000.0,
    "investment_base_krw": 196729220.0,
    "holding_count": 33,
    "nonzero_holding_count": 33
  },
  "summary": {
    "by_asset_class1": [
      {
        "asset_class1": "단기채권",
        "amount_krw_total": 60207677.0,
        "amount_krw_investment_base": 60207677.0,
        "pct_total_assets": 0.26886923,
        "pct_investment_base": 0.30604339
      },
      {
        "asset_class1": "지수",
        "amount_krw_total": 48745035.0,
        "amount_krw_investment_base": 48745035.0,
        "pct_total_assets": 0.21768055,
        "pct_investment_base": 0.2477773
      },
      {
        "asset_class1": "개별주식",
        "amount_krw_total": 32893964.0,
        "amount_krw_investment_base": 32893964.0,
        "pct_total_assets": 0.14689447,
        "pct_investment_base": 0.16720426
      },
      {
        "asset_class1": "예금",
        "amount_krw_total": 27200000.0,
        "amount_krw_investment_base": 0.0,
        "pct_total_assets": 0.12146695,
        "pct_investment_base": 0.0
      },
      {
        "asset_class1": "헷지",
        "amount_krw_total": 20667453.0,
        "amount_krw_investment_base": 20667453.0,
        "pct_total_assets": 0.09229458,
        "pct_investment_base": 0.10505533
      },
      {
        "asset_class1": "장기채권",
        "amount_krw_total": 19529260.0,
        "amount_krw_investment_base": 19529260.0,
        "pct_total_assets": 0.08721175,
        "pct_investment_base": 0.09926975
      },
      {
        "asset_class1": "현금",
        "amount_krw_total": 14685831.0,
        "amount_krw_investment_base": 14685831.0,
        "pct_total_assets": 0.06558247,
        "pct_investment_base": 0.07464997
      }
    ],
    "by_asset_class1_2": [
      {
        "asset_class1": "단기채권",
        "asset_class2": "초단기",
        "amount_krw_total": 60207677.0,
        "amount_krw_investment_base": 60207677.0,
        "pct_total_assets": 0.26886923,
        "pct_investment_base": 0.30604339
      },
      {
        "asset_class1": "지수",
        "asset_class2": "S&P500",
        "amount_krw_total": 36966275.0,
        "amount_krw_investment_base": 36966275.0,
        "pct_total_assets": 0.16508018,
        "pct_investment_base": 0.18790434
      },
      {
        "asset_class1": "예금",
        "asset_class2": "장기예금",
        "amount_krw_total": 27200000.0,
        "amount_krw_investment_base": 0.0,
        "pct_total_assets": 0.12146695,
        "pct_investment_base": 0.0
      },
      {
        "asset_class1": "헷지",
        "asset_class2": "금",
        "amount_krw_total": 20667453.0,
        "amount_krw_investment_base": 20667453.0,
        "pct_total_assets": 0.09229458,
        "pct_investment_base": 0.10505533
      },
      {
        "asset_class1": "장기채권",
        "asset_class2": "장기채",
        "amount_krw_total": 19529260.0,
        "amount_krw_investment_base": 19529260.0,
        "pct_total_assets": 0.08721175,
        "pct_investment_base": 0.09926975
      },
      {
        "asset_class1": "개별주식",
        "asset_class2": "IT",
        "amount_krw_total": 11980523.0,
        "amount_krw_investment_base": 11980523.0,
        "pct_total_assets": 0.05350138,
        "pct_investment_base": 0.06089854
      },
      {
        "asset_class1": "지수",
        "asset_class2": "S&P500동일가중",
        "amount_krw_total": 11778760.0,
        "amount_krw_investment_base": 11778760.0,
        "pct_total_assets": 0.05260037,
        "pct_investment_base": 0.05987296
      },
      {
        "asset_class1": "개별주식",
        "asset_class2": "반도체장비",
        "amount_krw_total": 11443997.0,
        "amount_krw_investment_base": 11443997.0,
        "pct_total_assets": 0.05110542,
        "pct_investment_base": 0.05817131
      },
      {
        "asset_class1": "현금",
        "asset_class2": "달러",
        "amount_krw_total": 10272396.0,
        "amount_krw_investment_base": 10272396.0,
        "pct_total_assets": 0.04587341,
        "pct_investment_base": 0.05221591
      },
      {
        "asset_class1": "현금",
        "asset_class2": "원화",
        "amount_krw_total": 4260976.0,
        "amount_krw_investment_base": 4260976.0,
        "pct_total_assets": 0.01902823,
        "pct_investment_base": 0.02165909
      },
      {
        "asset_class1": "개별주식",
        "asset_class2": "반도체설계",
        "amount_krw_total": 4124260.0,
        "amount_krw_investment_base": 4124260.0,
        "pct_total_assets": 0.01841769,
        "pct_investment_base": 0.02096415
      },
      {
        "asset_class1": "개별주식",
        "asset_class2": "헬스케어",
        "amount_krw_total": 3500184.0,
        "amount_krw_investment_base": 3500184.0,
        "pct_total_assets": 0.01563076,
        "pct_investment_base": 0.01779189
      },
      {
        "asset_class1": "개별주식",
        "asset_class2": "AI반도체",
        "amount_krw_total": 1845000.0,
        "amount_krw_investment_base": 1845000.0,
        "pct_total_assets": 0.00823921,
        "pct_investment_base": 0.00937837
      },
      {
        "asset_class1": "현금",
        "asset_class2": "엔화",
        "amount_krw_total": 152459.0,
        "amount_krw_investment_base": 152459.0,
        "pct_total_assets": 0.00068084,
        "pct_investment_base": 0.00077497
      }
    ],
    "by_investment_currency": [
      {
        "investment_currency": "원화",
        "amount_krw_total": 113624981.0,
        "amount_krw_investment_base": 86424981.0,
        "pct_total_assets": 0.50741471,
        "pct_investment_base": 0.43930933
      },
      {
        "investment_currency": "달러",
        "amount_krw_total": 102313211.0,
        "amount_krw_investment_base": 102313211.0,
        "pct_total_assets": 0.45689978,
        "pct_investment_base": 0.52007125
      },
      {
        "investment_currency": "엔화",
        "amount_krw_total": 7991028.0,
        "amount_krw_investment_base": 7991028.0,
        "pct_total_assets": 0.03568551,
        "pct_investment_base": 0.04061943
      }
    ],
    "by_listing_currency": [
      {
        "listing_currency": "KRW",
        "amount_krw_total": 128523741.0,
        "amount_krw_investment_base": 101323741.0,
        "pct_total_assets": 0.57394806,
        "pct_investment_base": 0.51504164
      },
      {
        "listing_currency": "USD",
        "amount_krw_total": 84955632.0,
        "amount_krw_investment_base": 84955632.0,
        "pct_total_assets": 0.37938609,
        "pct_investment_base": 0.43184044
      },
      {
        "listing_currency": "JPY",
        "amount_krw_total": 10449847.0,
        "amount_krw_investment_base": 10449847.0,
        "pct_total_assets": 0.04666585,
        "pct_investment_base": 0.05311792
      }
    ],
    "by_hedge_flag": [
      {
        "hedge_flag": "미분류",
        "amount_krw_total": 189842570.0,
        "amount_krw_investment_base": 162642570.0,
        "pct_total_assets": 0.84777936,
        "pct_investment_base": 0.82673316
      },
      {
        "hedge_flag": "O",
        "amount_krw_total": 34086650.0,
        "amount_krw_investment_base": 34086650.0,
        "pct_total_assets": 0.15222064,
        "pct_investment_base": 0.17326684
      }
    ],
    "by_owner": [
      {
        "owner": "동연",
        "amount_krw_total": 169364668.0,
        "amount_krw_investment_base": 169364668.0,
        "pct_total_assets": 0.75633126,
        "pct_investment_base": 0.86090245
      },
      {
        "owner": "완서",
        "amount_krw_total": 54564552.0,
        "amount_krw_investment_base": 27364552.0,
        "pct_total_assets": 0.24366874,
        "pct_investment_base": 0.13909755
      }
    ]
  },
  "holdings": [
    {
      "row_no": 8,
      "owner": "동연",
      "broker": "KB",
      "account": "CMA",
      "country": "",
      "investment_currency": "원화",
      "asset_class1": "현금",
      "asset_class2": "원화",
      "listing_currency": "KRW",
      "hedge_flag": "",
      "ticker": "",
      "name": "CMA현금",
      "quantity": null,
      "avg_price_foreign": null,
      "avg_price_krw": null,
      "purchase_amount_foreign": null,
      "purchase_amount_krw": 4080600.0,
      "current_price_foreign": null,
      "current_price_krw": null,
      "market_value_foreign": null,
      "market_value_krw": 4080600.0,
      "pnl_rate": 0.0,
      "pnl_amount_krw": 0.0,
      "pe": null,
      "forward_pe": null,
      "pb": null,
      "roe": null,
      "debt_ratio": null,
      "dividend_yield": null,
      "include_in_investment_base": true,
      "note": ""
    },
    {
      "row_no": 9,
      "owner": "동연",
      "broker": "KB",
      "account": "ISA",
      "country": "미국",
      "investment_currency": "원화",
      "asset_class1": "지수",
      "asset_class2": "S&P500",
      "listing_currency": "KRW",
      "hedge_flag": "O",
      "ticker": "449180.KS",
      "name": "KODEX 미국S&P500(H)",
      "quantity": 776.0,
      "avg_price_foreign": null,
      "avg_price_krw": 14872.0,
      "purchase_amount_foreign": null,
      "purchase_amount_krw": 11540672.0,
      "current_price_foreign": null,
      "current_price_krw": 16620.0,
      "market_value_foreign": null,
      "market_value_krw": 12897120.0,
      "pnl_rate": 0.11753631,
      "pnl_amount_krw": 1356448.0,
      "pe": null,
      "forward_pe": null,
      "pb": null,
      "roe": null,
      "debt_ratio": null,
      "dividend_yield": null,
      "include_in_investment_base": true,
      "note": ""
    },
    {
      "row_no": 10,
      "owner": "동연",
      "broker": "KB",
      "account": "ISA",
      "country": "",
      "investment_currency": "원화",
      "asset_class1": "헷지",
      "asset_class2": "금",
      "listing_currency": "KRW",
      "hedge_flag": "",
      "ticker": "411060.KS",
      "name": "ACE KRX금현물",
      "quantity": 321.0,
      "avg_price_foreign": null,
      "avg_price_krw": 31449.0,
      "purchase_amount_foreign": null,
      "purchase_amount_krw": 10095129.0,
      "current_price_foreign": null,
      "current_price_krw": 29630.0,
      "market_value_foreign": null,
      "market_value_krw": 9511230.0,
      "pnl_rate": -0.05783968,
      "pnl_amount_krw": -583899.0,
      "pe": null,
      "forward_pe": null,
      "pb": null,
      "roe": null,
      "debt_ratio": null,
      "dividend_yield": null,
      "include_in_investment_base": true,
      "note": ""
    },
    {
      "row_no": 11,
      "owner": "동연",
      "broker": "KB",
      "account": "ISA",
      "country": "미국",
      "investment_currency": "달러",
      "asset_class1": "지수",
      "asset_class2": "S&P500동일가중",
      "listing_currency": "KRW",
      "hedge_flag": "",
      "ticker": "488500.KS",
      "name": "TIGER 미국S&P500동일가중",
      "quantity": 514.0,
      "avg_price_foreign": null,
      "avg_price_krw": 12432.0,
      "purchase_amount_foreign": null,
      "purchase_amount_krw": 6390048.0,
      "current_price_foreign": null,
      "current_price_krw": 13570.0,
      "market_value_foreign": null,
      "market_value_krw": 6974980.0,
      "pnl_rate": 0.09153797,
      "pnl_amount_krw": 584932.0,
      "pe": null,
      "forward_pe": null,
      "pb": null,
      "roe": null,
      "debt_ratio": null,
      "dividend_yield": null,
      "include_in_investment_base": true,
      "note": ""
    },
    {
      "row_no": 12,
      "owner": "동연",
      "broker": "KB",
      "account": "ISA",
      "country": "",
      "investment_currency": "원화",
      "asset_class1": "현금",
      "asset_class2": "원화",
      "listing_currency": "KRW",
      "hedge_flag": "",
      "ticker": "",
      "name": "ISA현금",
      "quantity": null,
      "avg_price_foreign": null,
      "avg_price_krw": null,
      "purchase_amount_foreign": null,
      "purchase_amount_krw": 78156.0,
      "current_price_foreign": null,
      "current_price_krw": null,
      "market_value_foreign": null,
      "market_value_krw": 78156.0,
      "pnl_rate": 0.0,
      "pnl_amount_krw": 0.0,
      "pe": null,
      "forward_pe": null,
      "pb": null,
      "roe": null,
      "debt_ratio": null,
      "dividend_yield": null,
      "include_in_investment_base": true,
      "note": ""
    },
    {
      "row_no": 13,
      "owner": "동연",
      "broker": "KB",
      "account": "ISA",
      "country": "미국",
      "investment_currency": "원화",
      "asset_class1": "지수",
      "asset_class2": "S&P500",
      "listing_currency": "KRW",
      "hedge_flag": "",
      "ticker": "379800.KS",
      "name": "KODEX 미국S&P500",
      "quantity": 162.0,
      "avg_price_foreign": null,
      "avg_price_krw": 23416.0,
      "purchase_amount_foreign": null,
      "purchase_amount_krw": 3793392.0,
      "current_price_foreign": null,
      "current_price_krw": 26015.0,
      "market_value_foreign": null,
      "market_value_krw": 4214430.0,
      "pnl_rate": 0.11099248,
      "pnl_amount_krw": 421038.0,
      "pe": null,
      "forward_pe": null,
      "pb": null,
      "roe": null,
      "debt_ratio": null,
      "dividend_yield": null,
      "include_in_investment_base": true,
      "note": ""
    },
    {
      "row_no": 14,
      "owner": "동연",
      "broker": "KB",
      "account": "ISA",
      "country": "한국",
      "investment_currency": "원화",
      "asset_class1": "단기채권",
      "asset_class2": "초단기",
      "listing_currency": "KRW",
      "hedge_flag": "",
      "ticker": "459580.KS",
      "name": "KODEX CD금리액티브(합성)",
      "quantity": 18.0,
      "avg_price_foreign": null,
      "avg_price_krw": 1075325.0,
      "purchase_amount_foreign": null,
      "purchase_amount_krw": 19355850.0,
      "current_price_foreign": null,
      "current_price_krw": 1074245.0,
      "market_value_foreign": null,
      "market_value_krw": 19336410.0,
      "pnl_rate": -0.00100435,
      "pnl_amount_krw": -19440.0,
      "pe": null,
      "forward_pe": null,
      "pb": null,
      "roe": null,
      "debt_ratio": null,
      "dividend_yield": null,
      "include_in_investment_base": true,
      "note": ""
    },
    {
      "row_no": 15,
      "owner": "동연",
      "broker": "키움",
      "account": "위탁종합",
      "country": "미국",
      "investment_currency": "달러",
      "asset_class1": "단기채권",
      "asset_class2": "초단기",
      "listing_currency": "USD",
      "hedge_flag": "",
      "ticker": "SGOV",
      "name": "iShares 0-3 Month Treasury Bond ETF",
      "quantity": 236.0,
      "avg_price_foreign": 100.5358,
      "avg_price_krw": 155509.7808,
      "purchase_amount_foreign": 23726.4488,
      "purchase_amount_krw": 36700308.0,
      "current_price_foreign": 100.44999695,
      "current_price_krw": 155377.0598,
      "market_value_foreign": 23706.19927979,
      "market_value_krw": 36668986.0,
      "pnl_rate": -0.00085346,
      "pnl_amount_krw": -31322.0,
      "pe": null,
      "forward_pe": null,
      "pb": null,
      "roe": null,
      "debt_ratio": null,
      "dividend_yield": 0.039,
      "include_in_investment_base": true,
      "note": ""
    },
    {
      "row_no": 16,
      "owner": "동연",
      "broker": "키움",
      "account": "위탁종합",
      "country": "미국",
      "investment_currency": "달러",
      "asset_class1": "단기채권",
      "asset_class2": "초단기",
      "listing_currency": "USD",
      "hedge_flag": "",
      "ticker": "VTIP",
      "name": "Vanguard Short-Term Inflation-Protected Securities Index Fund ETF Shares",
      "quantity": 54.0,
      "avg_price_foreign": 50.37,
      "avg_price_krw": 77912.8197,
      "purchase_amount_foreign": 2719.98,
      "purchase_amount_krw": 4207292.0,
      "current_price_foreign": 50.31000137,
      "current_price_krw": 77820.0132,
      "market_value_foreign": 2716.74007416,
      "market_value_krw": 4202281.0,
      "pnl_rate": -0.00119116,
      "pnl_amount_krw": -5012.0,
      "pe": null,
      "forward_pe": null,
      "pb": null,
      "roe": null,
      "debt_ratio": null,
      "dividend_yield": 0.0359,
      "include_in_investment_base": true,
      "note": ""
    },
    {
      "row_no": 17,
      "owner": "동연",
      "broker": "KB",
      "account": "ISA",
      "country": "미국",
      "investment_currency": "달러",
      "asset_class1": "장기채권",
      "asset_class2": "장기채",
      "listing_currency": "KRW",
      "hedge_flag": "",
      "ticker": "476760.KS",
      "name": "ACE 미국30년국채액티브",
      "quantity": 300.0,
      "avg_price_foreign": null,
      "avg_price_krw": 10215.0,
      "purchase_amount_foreign": null,
      "purchase_amount_krw": 3064500.0,
      "current_price_foreign": null,
      "current_price_krw": 10400.0,
      "market_value_foreign": null,
      "market_value_krw": 3120000.0,
      "pnl_rate": 0.01811062,
      "pnl_amount_krw": 55500.0,
      "pe": null,
      "forward_pe": null,
      "pb": null,
      "roe": null,
      "debt_ratio": null,
      "dividend_yield": null,
      "include_in_investment_base": true,
      "note": ""
    },
    {
      "row_no": 18,
      "owner": "동연",
      "broker": "키움",
      "account": "위탁종합",
      "country": "",
      "investment_currency": "엔화",
      "asset_class1": "헷지",
      "asset_class2": "금",
      "listing_currency": "JPY",
      "hedge_flag": "",
      "ticker": "1540.T",
      "name": "MITSUBICHI JAPAN PHYSICAL GOLD ETF",
      "quantity": 39.0,
      "avg_price_foreign": 21892.3359,
      "avg_price_krw": 210632.7314,
      "purchase_amount_foreign": 853801.1001,
      "purchase_amount_krw": 8214677.0,
      "current_price_foreign": 20890.0,
      "current_price_krw": 200988.957,
      "market_value_foreign": 814710.0,
      "market_value_krw": 7838569.0,
      "pnl_rate": -0.04578479,
      "pnl_amount_krw": -376107.0,
      "pe": null,
      "forward_pe": null,
      "pb": null,
      "roe": null,
      "debt_ratio": null,
      "dividend_yield": null,
      "include_in_investment_base": true,
      "note": ""
    },
    {
      "row_no": 19,
      "owner": "동연",
      "broker": "키움",
      "account": "위탁종합",
      "country": "",
      "investment_currency": "달러",
      "asset_class1": "헷지",
      "asset_class2": "금",
      "listing_currency": "JPY",
      "hedge_flag": "",
      "ticker": "1326.T",
      "name": "SPDR GOLD SHARES",
      "quantity": 4.0,
      "avg_price_foreign": 58881.6,
      "avg_price_krw": 566517.5381,
      "purchase_amount_foreign": 235526.4,
      "purchase_amount_krw": 2266070.0,
      "current_price_foreign": 63890.0,
      "current_price_krw": 614704.857,
      "market_value_foreign": 255560.0,
      "market_value_krw": 2458819.0,
      "pnl_rate": 0.08505883,
      "pnl_amount_krw": 192749.0,
      "pe": null,
      "forward_pe": null,
      "pb": null,
      "roe": null,
      "debt_ratio": null,
      "dividend_yield": 0.0,
      "include_in_investment_base": true,
      "note": ""
    },
    {
      "row_no": 20,
      "owner": "동연",
      "broker": "키움",
      "account": "위탁종합",
      "country": "",
      "investment_currency": "엔화",
      "asset_class1": "현금",
      "asset_class2": "엔화",
      "listing_currency": "JPY",
      "hedge_flag": "",
      "ticker": "",
      "name": "키움엔화현금",
      "quantity": null,
      "avg_price_foreign": null,
      "avg_price_krw": null,
      "purchase_amount_foreign": 15846.0,
      "purchase_amount_krw": 152459.0,
      "current_price_foreign": null,
      "current_price_krw": null,
      "market_value_foreign": 15846.0,
      "market_value_krw": 152459.0,
      "pnl_rate": 0.0,
      "pnl_amount_krw": 0.0,
      "pe": null,
      "forward_pe": null,
      "pb": null,
      "roe": null,
      "debt_ratio": null,
      "dividend_yield": null,
      "include_in_investment_base": true,
      "note": ""
    },
    {
      "row_no": 21,
      "owner": "동연",
      "broker": "KB",
      "account": "ISA",
      "country": "미국",
      "investment_currency": "원화",
      "asset_class1": "장기채권",
      "asset_class2": "장기채",
      "listing_currency": "KRW",
      "hedge_flag": "O",
      "ticker": "453850.KS",
      "name": "ACE 미국30년국채액티브(H)",
      "quantity": 949.0,
      "avg_price_foreign": null,
      "avg_price_krw": 7381.0,
      "purchase_amount_foreign": null,
      "purchase_amount_krw": 7004569.0,
      "current_price_foreign": null,
      "current_price_krw": 7410.0,
      "market_value_foreign": null,
      "market_value_krw": 7032090.0,
      "pnl_rate": 0.00392901,
      "pnl_amount_krw": 27521.0,
      "pe": null,
      "forward_pe": null,
      "pb": null,
      "roe": null,
      "debt_ratio": null,
      "dividend_yield": null,
      "include_in_investment_base": true,
      "note": ""
    },
    {
      "row_no": 22,
      "owner": "동연",
      "broker": "KB",
      "account": "ISA",
      "country": "한국",
      "investment_currency": "원화",
      "asset_class1": "장기채권",
      "asset_class2": "장기채",
      "listing_currency": "KRW",
      "hedge_flag": "",
      "ticker": "439870.KS",
      "name": "KODEX 국고채30년액티브",
      "quantity": 73.0,
      "avg_price_foreign": null,
      "avg_price_krw": 91318.0,
      "purchase_amount_foreign": null,
      "purchase_amount_krw": 6666214.0,
      "current_price_foreign": null,
      "current_price_krw": 90605.0,
      "market_value_foreign": null,
      "market_value_krw": 6614165.0,
      "pnl_rate": -0.00780788,
      "pnl_amount_krw": -52049.0,
      "pe": null,
      "forward_pe": null,
      "pb": null,
      "roe": null,
      "debt_ratio": null,
      "dividend_yield": null,
      "include_in_investment_base": true,
      "note": ""
    },
    {
      "row_no": 23,
      "owner": "동연",
      "broker": "키움",
      "account": "위탁종합",
      "country": "",
      "investment_currency": "달러",
      "asset_class1": "현금",
      "asset_class2": "달러",
      "listing_currency": "USD",
      "hedge_flag": "",
      "ticker": "",
      "name": "키움달러현금",
      "quantity": null,
      "avg_price_foreign": null,
      "avg_price_krw": null,
      "purchase_amount_foreign": 6641.02,
      "purchase_amount_krw": 10272396.0,
      "current_price_foreign": null,
      "current_price_krw": null,
      "market_value_foreign": 6641.02,
      "market_value_krw": 10272396.0,
      "pnl_rate": 0.0,
      "pnl_amount_krw": 0.0,
      "pe": null,
      "forward_pe": null,
      "pb": null,
      "roe": null,
      "debt_ratio": null,
      "dividend_yield": null,
      "include_in_investment_base": true,
      "note": ""
    },
    {
      "row_no": 24,
      "owner": "동연",
      "broker": "키움",
      "account": "위탁종합",
      "country": "미국",
      "investment_currency": "달러",
      "asset_class1": "개별주식",
      "asset_class2": "IT",
      "listing_currency": "USD",
      "hedge_flag": "",
      "ticker": "AMZN",
      "name": "아마존닷컴",
      "quantity": 18.0,
      "avg_price_foreign": 201.3106,
      "avg_price_krw": 311389.2492,
      "purchase_amount_foreign": 3623.5908,
      "purchase_amount_krw": 5605006.0,
      "current_price_foreign": 246.02999878,
      "current_price_krw": 380561.6624,
      "market_value_foreign": 4428.53997803,
      "market_value_krw": 6850110.0,
      "pnl_rate": 0.2221413,
      "pnl_amount_krw": 1245103.0,
      "pe": 31.664093,
      "forward_pe": 24.942696,
      "pb": 5.987151,
      "roe": 0.24285,
      "debt_ratio": 53.3,
      "dividend_yield": null,
      "include_in_investment_base": true,
      "note": ""
    },
    {
      "row_no": 25,
      "owner": "동연",
      "broker": "키움",
      "account": "위탁종합",
      "country": "미국",
      "investment_currency": "달러",
      "asset_class1": "개별주식",
      "asset_class2": "반도체장비",
      "listing_currency": "USD",
      "hedge_flag": "",
      "ticker": "AMAT",
      "name": "어플라이드 머티어리얼즈",
      "quantity": 9.0,
      "avg_price_foreign": 349.0124,
      "avg_price_krw": 539855.8704,
      "purchase_amount_foreign": 3141.1116,
      "purchase_amount_krw": 4858703.0,
      "current_price_foreign": 453.01000977,
      "current_price_krw": 700720.4132,
      "market_value_foreign": 4077.09008789,
      "market_value_krw": 6306484.0,
      "pnl_rate": 0.29797683,
      "pnl_amount_krw": 1447781.0,
      "pe": 42.53615,
      "forward_pe": 28.016016,
      "pb": 15.043169,
      "roe": 0.39692003,
      "debt_ratio": 30.399,
      "dividend_yield": 0.00467981,
      "include_in_investment_base": true,
      "note": "반도체 미세공정 및 패키징 장비 필수재"
    },
    {
      "row_no": 26,
      "owner": "동연",
      "broker": "키움",
      "account": "위탁종합",
      "country": "미국",
      "investment_currency": "달러",
      "asset_class1": "개별주식",
      "asset_class2": "IT",
      "listing_currency": "USD",
      "hedge_flag": "",
      "ticker": "GOOGL",
      "name": "알파벳 A",
      "quantity": 9.0,
      "avg_price_foreign": 314.4925,
      "avg_price_krw": 486460.1439,
      "purchase_amount_foreign": 2830.4325,
      "purchase_amount_krw": 4378141.0,
      "current_price_foreign": 368.52999878,
      "current_price_krw": 570045.8874,
      "market_value_foreign": 3316.76998901,
      "market_value_krw": 5130413.0,
      "pnl_rate": 0.17182444,
      "pnl_amount_krw": 752272.0,
      "pe": 28.089176,
      "forward_pe": 25.484406,
      "pb": 9.326568,
      "roe": 0.38884997,
      "debt_ratio": 20.026,
      "dividend_yield": 0.00238787,
      "include_in_investment_base": true,
      "note": ""
    },
    {
      "row_no": 27,
      "owner": "동연",
      "broker": "키움",
      "account": "위탁종합",
      "country": "미국",
      "investment_currency": "달러",
      "asset_class1": "개별주식",
      "asset_class2": "반도체장비",
      "listing_currency": "USD",
      "hedge_flag": "",
      "ticker": "TSM",
      "name": "TSMC(ADR)",
      "quantity": 8.0,
      "avg_price_foreign": 362.8433,
      "avg_price_krw": 561249.6449,
      "purchase_amount_foreign": 2902.7464,
      "purchase_amount_krw": 4489997.0,
      "current_price_foreign": 415.17001343,
      "current_price_krw": 642189.1285,
      "market_value_foreign": 3321.36010742,
      "market_value_krw": 5137513.0,
      "pnl_rate": 0.14421298,
      "pnl_amount_krw": 647516.0,
      "pe": 35.575836,
      "forward_pe": 21.259285,
      "pb": 63.50735,
      "roe": 0.3621,
      "debt_ratio": 18.447,
      "dividend_yield": 0.00915288,
      "include_in_investment_base": true,
      "note": "반도체 미세공정 및 패키징 장비 필수재"
    },
    {
      "row_no": 28,
      "owner": "동연",
      "broker": "키움",
      "account": "위탁종합",
      "country": "미국",
      "investment_currency": "달러",
      "asset_class1": "개별주식",
      "asset_class2": "반도체설계",
      "listing_currency": "USD",
      "hedge_flag": "",
      "ticker": "NVDA",
      "name": "엔비디아",
      "quantity": 13.0,
      "avg_price_foreign": 186.2285,
      "avg_price_krw": 288060.1061,
      "purchase_amount_foreign": 2420.9705,
      "purchase_amount_krw": 3744781.0,
      "current_price_foreign": 205.1000061,
      "current_price_krw": 317250.7404,
      "market_value_foreign": 2666.30007935,
      "market_value_krw": 4124260.0,
      "pnl_rate": 0.10133522,
      "pnl_amount_krw": 379478.0,
      "pe": 31.457056,
      "forward_pe": 16.172209,
      "pb": 31.69036,
      "roe": 1.14288,
      "debt_ratio": 6.555,
      "dividend_yield": 0.00487567,
      "include_in_investment_base": true,
      "note": ""
    },
    {
      "row_no": 29,
      "owner": "동연",
      "broker": "키움",
      "account": "위탁종합",
      "country": "미국",
      "investment_currency": "달러",
      "asset_class1": "개별주식",
      "asset_class2": "헬스케어",
      "listing_currency": "USD",
      "hedge_flag": "",
      "ticker": "LLY",
      "name": "일라이 릴리",
      "quantity": 2.0,
      "avg_price_foreign": 912.0,
      "avg_price_krw": 1410690.72,
      "purchase_amount_foreign": 1824.0,
      "purchase_amount_krw": 2821381.0,
      "current_price_foreign": 1131.42004395,
      "current_price_krw": 1750091.8382,
      "market_value_foreign": 2262.84008789,
      "market_value_krw": 3500184.0,
      "pnl_rate": 0.24059215,
      "pnl_amount_krw": 678802.0,
      "pe": 40.164005,
      "forward_pe": 25.43093,
      "pb": 32.40313,
      "roe": 1.07459,
      "debt_ratio": 139.015,
      "dividend_yield": 0.00611621,
      "include_in_investment_base": true,
      "note": ""
    },
    {
      "row_no": 30,
      "owner": "동연",
      "broker": "키움",
      "account": "위탁종합",
      "country": "미국",
      "investment_currency": "달러",
      "asset_class1": "장기채권",
      "asset_class2": "장기채",
      "listing_currency": "USD",
      "hedge_flag": "",
      "ticker": "TLT",
      "name": "미국 +20년 장기 국채",
      "quantity": 21.0,
      "avg_price_foreign": 85.6859,
      "avg_price_krw": 132539.807,
      "purchase_amount_foreign": 1799.4039,
      "purchase_amount_krw": 2783336.0,
      "current_price_foreign": 85.05999756,
      "current_price_krw": 131571.6548,
      "market_value_foreign": 1786.25994873,
      "market_value_krw": 2763005.0,
      "pnl_rate": -0.00730461,
      "pnl_amount_krw": -20331.0,
      "pe": null,
      "forward_pe": null,
      "pb": null,
      "roe": null,
      "debt_ratio": null,
      "dividend_yield": 0.0455,
      "include_in_investment_base": true,
      "note": ""
    },
    {
      "row_no": 31,
      "owner": "동연",
      "broker": "키움",
      "account": "위탁종합",
      "country": "",
      "investment_currency": "원화",
      "asset_class1": "현금",
      "asset_class2": "원화",
      "listing_currency": "KRW",
      "hedge_flag": "",
      "ticker": "",
      "name": "키움원화현금",
      "quantity": null,
      "avg_price_foreign": null,
      "avg_price_krw": null,
      "purchase_amount_foreign": null,
      "purchase_amount_krw": 100008.0,
      "current_price_foreign": null,
      "current_price_krw": null,
      "market_value_foreign": null,
      "market_value_krw": 100008.0,
      "pnl_rate": 0.0,
      "pnl_amount_krw": 0.0,
      "pe": null,
      "forward_pe": null,
      "pb": null,
      "roe": null,
      "debt_ratio": null,
      "dividend_yield": null,
      "include_in_investment_base": true,
      "note": ""
    },
    {
      "row_no": 32,
      "owner": "완서",
      "broker": "키움",
      "account": "ISA",
      "country": "미국",
      "investment_currency": "원화",
      "asset_class1": "지수",
      "asset_class2": "S&P500",
      "listing_currency": "KRW",
      "hedge_flag": "O",
      "ticker": "453330.KS",
      "name": "RISE 미국 S&P500(H)",
      "quantity": 728.0,
      "avg_price_foreign": null,
      "avg_price_krw": 16523.0,
      "purchase_amount_foreign": null,
      "purchase_amount_krw": 12028744.0,
      "current_price_foreign": null,
      "current_price_krw": 17575.0,
      "market_value_foreign": null,
      "market_value_krw": 12794600.0,
      "pnl_rate": 0.06366883,
      "pnl_amount_krw": 765856.0,
      "pe": null,
      "forward_pe": null,
      "pb": null,
      "roe": null,
      "debt_ratio": null,
      "dividend_yield": null,
      "include_in_investment_base": true,
      "note": ""
    },
    {
      "row_no": 33,
      "owner": "완서",
      "broker": "키움",
      "account": "ISA",
      "country": "미국",
      "investment_currency": "원화",
      "asset_class1": "지수",
      "asset_class2": "S&P500",
      "listing_currency": "KRW",
      "hedge_flag": "O",
      "ticker": "449180.KS",
      "name": "KODEX 미국S&P500(H)",
      "quantity": 82.0,
      "avg_price_foreign": null,
      "avg_price_krw": 16595.0,
      "purchase_amount_foreign": null,
      "purchase_amount_krw": 1360790.0,
      "current_price_foreign": null,
      "current_price_krw": 16620.0,
      "market_value_foreign": null,
      "market_value_krw": 1362840.0,
      "pnl_rate": 0.00150648,
      "pnl_amount_krw": 2050.0,
      "pe": null,
      "forward_pe": null,
      "pb": null,
      "roe": null,
      "debt_ratio": null,
      "dividend_yield": null,
      "include_in_investment_base": true,
      "note": ""
    },
    {
      "row_no": 34,
      "owner": "완서",
      "broker": "키움",
      "account": "ISA",
      "country": "미국",
      "investment_currency": "원화",
      "asset_class1": "지수",
      "asset_class2": "S&P500",
      "listing_currency": "KRW",
      "hedge_flag": "",
      "ticker": "379800.KS",
      "name": "KODEX 미국S&P500",
      "quantity": 219.0,
      "avg_price_foreign": null,
      "avg_price_krw": 25104.0,
      "purchase_amount_foreign": null,
      "purchase_amount_krw": 5497776.0,
      "current_price_foreign": null,
      "current_price_krw": 26015.0,
      "market_value_foreign": null,
      "market_value_krw": 5697285.0,
      "pnl_rate": 0.03628904,
      "pnl_amount_krw": 199509.0,
      "pe": null,
      "forward_pe": null,
      "pb": null,
      "roe": null,
      "debt_ratio": null,
      "dividend_yield": null,
      "include_in_investment_base": true,
      "note": ""
    },
    {
      "row_no": 35,
      "owner": "완서",
      "broker": "키움",
      "account": "ISA",
      "country": "",
      "investment_currency": "원화",
      "asset_class1": "헷지",
      "asset_class2": "금",
      "listing_currency": "KRW",
      "hedge_flag": "",
      "ticker": "411060.KS",
      "name": "ACE KRX금현물",
      "quantity": 29.0,
      "avg_price_foreign": null,
      "avg_price_krw": 30095.0,
      "purchase_amount_foreign": null,
      "purchase_amount_krw": 872755.0,
      "current_price_foreign": null,
      "current_price_krw": 29615.0,
      "market_value_foreign": null,
      "market_value_krw": 858835.0,
      "pnl_rate": -0.01594949,
      "pnl_amount_krw": -13920.0,
      "pe": null,
      "forward_pe": null,
      "pb": null,
      "roe": null,
      "debt_ratio": null,
      "dividend_yield": null,
      "include_in_investment_base": true,
      "note": ""
    },
    {
      "row_no": 36,
      "owner": "완서",
      "broker": "키움",
      "account": "ISA",
      "country": "",
      "investment_currency": "원화",
      "asset_class1": "현금",
      "asset_class2": "원화",
      "listing_currency": "KRW",
      "hedge_flag": "",
      "ticker": "",
      "name": "키움원화현금",
      "quantity": null,
      "avg_price_foreign": null,
      "avg_price_krw": null,
      "purchase_amount_foreign": null,
      "purchase_amount_krw": 2212.0,
      "current_price_foreign": null,
      "current_price_krw": null,
      "market_value_foreign": null,
      "market_value_krw": 2212.0,
      "pnl_rate": 0.0,
      "pnl_amount_krw": 0.0,
      "pe": null,
      "forward_pe": null,
      "pb": null,
      "roe": null,
      "debt_ratio": null,
      "dividend_yield": null,
      "include_in_investment_base": true,
      "note": ""
    },
    {
      "row_no": 37,
      "owner": "완서",
      "broker": "키움",
      "account": "ISA",
      "country": "한국",
      "investment_currency": "원화",
      "asset_class1": "개별주식",
      "asset_class2": "AI반도체",
      "listing_currency": "KRW",
      "hedge_flag": "",
      "ticker": "005930.KS",
      "name": "삼성전자",
      "quantity": 6.0,
      "avg_price_foreign": null,
      "avg_price_krw": 215700.0,
      "purchase_amount_foreign": null,
      "purchase_amount_krw": 1294200.0,
      "current_price_foreign": null,
      "current_price_krw": 307500.0,
      "market_value_foreign": null,
      "market_value_krw": 1845000.0,
      "pnl_rate": 0.4255911,
      "pnl_amount_krw": 550800.0,
      "pe": null,
      "forward_pe": 5.458445,
      "pb": null,
      "roe": 0.18855,
      "debt_ratio": 5.782,
      "dividend_yield": 0.00483902,
      "include_in_investment_base": true,
      "note": ""
    },
    {
      "row_no": 38,
      "owner": "완서",
      "broker": "키움",
      "account": "ISA",
      "country": "미국",
      "investment_currency": "달러",
      "asset_class1": "지수",
      "asset_class2": "S&P500동일가중",
      "listing_currency": "KRW",
      "hedge_flag": "",
      "ticker": "488500.KS",
      "name": "TIGER 미국S&P500동일가중",
      "quantity": 354.0,
      "avg_price_foreign": null,
      "avg_price_krw": 12700.0,
      "purchase_amount_foreign": null,
      "purchase_amount_krw": 4495800.0,
      "current_price_foreign": null,
      "current_price_krw": 13570.0,
      "market_value_foreign": null,
      "market_value_krw": 4803780.0,
      "pnl_rate": 0.06850394,
      "pnl_amount_krw": 307980.0,
      "pe": null,
      "forward_pe": null,
      "pb": null,
      "roe": null,
      "debt_ratio": null,
      "dividend_yield": null,
      "include_in_investment_base": true,
      "note": ""
    },
    {
      "row_no": 39,
      "owner": "완서",
      "broker": "기타",
      "account": "주택청약",
      "country": "",
      "investment_currency": "원화",
      "asset_class1": "예금",
      "asset_class2": "장기예금",
      "listing_currency": "KRW",
      "hedge_flag": "",
      "ticker": "",
      "name": "주택청약저축",
      "quantity": null,
      "avg_price_foreign": null,
      "avg_price_krw": null,
      "purchase_amount_foreign": null,
      "purchase_amount_krw": 12200000.0,
      "current_price_foreign": null,
      "current_price_krw": null,
      "market_value_foreign": null,
      "market_value_krw": 12200000.0,
      "pnl_rate": 0.0,
      "pnl_amount_krw": 0.0,
      "pe": null,
      "forward_pe": null,
      "pb": null,
      "roe": null,
      "debt_ratio": null,
      "dividend_yield": null,
      "include_in_investment_base": false,
      "note": ""
    },
    {
      "row_no": 40,
      "owner": "완서",
      "broker": "기타",
      "account": "청년도약",
      "country": "",
      "investment_currency": "원화",
      "asset_class1": "예금",
      "asset_class2": "장기예금",
      "listing_currency": "KRW",
      "hedge_flag": "",
      "ticker": "",
      "name": "청년도약계좌(월60만원)",
      "quantity": null,
      "avg_price_foreign": null,
      "avg_price_krw": null,
      "purchase_amount_foreign": null,
      "purchase_amount_krw": 15000000.0,
      "current_price_foreign": null,
      "current_price_krw": null,
      "market_value_foreign": null,
      "market_value_krw": 15000000.0,
      "pnl_rate": 0.0,
      "pnl_amount_krw": 0.0,
      "pe": null,
      "forward_pe": null,
      "pb": null,
      "roe": null,
      "debt_ratio": null,
      "dividend_yield": null,
      "include_in_investment_base": false,
      "note": "(5년만기:29년5월)5월 반영"
    }
  ]
}