[
  {
    "row_no": 8,
    "owner": "동연",
    "broker": "KB",
    "account": "CMA",
    "country": "",
    "investment_currency": "원화",
    "asset_class1": "현금",
    "asset_class2": "원화",
    "listing_currency": "KRW",
    "hedge_flag": "",
    "ticker": "",
    "name": "CMA현금",
    "quantity": null,
    "avg_price_foreign": null,
    "avg_price_krw": null,
    "purchase_amount_foreign": null,
    "purchase_amount_krw": 14374238.0,
    "current_price_foreign": null,
    "current_price_krw": null,
    "market_value_foreign": null,
    "market_value_krw": 14374238.0,
    "pnl_rate": 0.0,
    "pnl_amount_krw": 0.0,
    "pe": null,
    "forward_pe": null,
    "pb": null,
    "roe": null,
    "debt_ratio": null,
    "dividend_yield": null,
    "include_in_investment_base": true,
    "note": ""
  },
  {
    "row_no": 9,
    "owner": "동연",
    "broker": "KB",
    "account": "ISA",
    "country": "",
    "investment_currency": "원화",
    "asset_class1": "지수",
    "asset_class2": "S&P500",
    "listing_currency": "KRW",
    "hedge_flag": "O",
    "ticker": "449180.KS",
    "name": "KODEX 미국S&P500(H)",
    "quantity": 776.0,
    "avg_price_foreign": null,
    "avg_price_krw": 14872.0,
    "purchase_amount_foreign": null,
    "purchase_amount_krw": 11540672.0,
    "current_price_foreign": null,
    "current_price_krw": 16635.0,
    "market_value_foreign": null,
    "market_value_krw": 12908760.0,
    "pnl_rate": 0.11854492,
    "pnl_amount_krw": 1368088.0,
    "pe": null,
    "forward_pe": null,
    "pb": null,
    "roe": null,
    "debt_ratio": null,
    "dividend_yield": null,
    "include_in_investment_base": true,
    "note": ""
  },
  {
    "row_no": 10,
    "owner": "동연",
    "broker": "KB",
    "account": "ISA",
    "country": "",
    "investment_currency": "원화",
    "asset_class1": "헷지",
    "asset_class2": "금",
    "listing_currency": "KRW",
    "hedge_flag": "",
    "ticker": "411060.KS",
    "name": "ACE KRX금현물",
    "quantity": 285.0,
    "avg_price_foreign": null,
    "avg_price_krw": 31621.0,
    "purchase_amount_foreign": null,
    "purchase_amount_krw": 9011985.0,
    "current_price_foreign": null,
    "current_price_krw": 31220.0,
    "market_value_foreign": null,
    "market_value_krw": 8897700.0,
    "pnl_rate": -0.01268145,
    "pnl_amount_krw": -114285.0,
    "pe": null,
    "forward_pe": null,
    "pb": null,
    "roe": null,
    "debt_ratio": null,
    "dividend_yield": null,
    "include_in_investment_base": true,
    "note": ""
  },
  {
    "row_no": 11,
    "owner": "동연",
    "broker": "KB",
    "account": "ISA",
    "country": "",
    "investment_currency": "원화",
    "asset_class1": "현금",
    "asset_class2": "원화",
    "listing_currency": "KRW",
    "hedge_flag": "",
    "ticker": "",
    "name": "ISA현금",
    "quantity": null,
    "avg_price_foreign": null,
    "avg_price_krw": null,
    "purchase_amount_foreign": null,
    "purchase_amount_krw": 5108535.0,
    "current_price_foreign": null,
    "current_price_krw": null,
    "market_value_foreign": null,
    "market_value_krw": 5108535.0,
    "pnl_rate": 0.0,
    "pnl_amount_krw": 0.0,
    "pe": null,
    "forward_pe": null,
    "pb": null,
    "roe": null,
    "debt_ratio": null,
    "dividend_yield": null,
    "include_in_investment_base": true,
    "note": ""
  },
  {
    "row_no": 12,
    "owner": "동연",
    "broker": "KB",
    "account": "ISA",
    "country": "",
    "investment_currency": "달러",
    "asset_class1": "지수",
    "asset_class2": "S&P500동일가중",
    "listing_currency": "KRW",
    "hedge_flag": "",
    "ticker": "488500.KS",
    "name": "TIGER 미국S&P500동일가중",
    "quantity": 514.0,
    "avg_price_foreign": null,
    "avg_price_krw": 12432.0,
    "purchase_amount_foreign": null,
    "purchase_amount_krw": 6390048.0,
    "current_price_foreign": null,
    "current_price_krw": 12850.0,
    "market_value_foreign": null,
    "market_value_krw": 6604900.0,
    "pnl_rate": 0.03362291,
    "pnl_amount_krw": 214852.0,
    "pe": null,
    "forward_pe": null,
    "pb": null,
    "roe": null,
    "debt_ratio": null,
    "dividend_yield": null,
    "include_in_investment_base": true,
    "note": ""
  },
  {
    "row_no": 13,
    "owner": "동연",
    "broker": "KB",
    "account": "ISA",
    "country": "",
    "investment_currency": "원화",
    "asset_class1": "지수",
    "asset_class2": "S&P500",
    "listing_currency": "KRW",
    "hedge_flag": "",
    "ticker": "379800.KS",
    "name": "KODEX 미국S&P500",
    "quantity": 162.0,
    "avg_price_foreign": null,
    "avg_price_krw": 23416.0,
    "purchase_amount_foreign": null,
    "purchase_amount_krw": 3793392.0,
    "current_price_foreign": null,
    "current_price_krw": 25000.0,
    "market_value_foreign": null,
    "market_value_krw": 4050000.0,
    "pnl_rate": 0.06764605,
    "pnl_amount_krw": 256608.0,
    "pe": null,
    "forward_pe": null,
    "pb": null,
    "roe": null,
    "debt_ratio": null,
    "dividend_yield": null,
    "include_in_investment_base": true,
    "note": ""
  },
  {
    "row_no": 14,
    "owner": "동연",
    "broker": "KB",
    "account": "ISA",
    "country": "",
    "investment_currency": "달러",
    "asset_class1": "채권",
    "asset_class2": "장기채",
    "listing_currency": "KRW",
    "hedge_flag": "",
    "ticker": "476760.KS",
    "name": "ACE 미국30년국채액티브",
    "quantity": 300.0,
    "avg_price_foreign": null,
    "avg_price_krw": 10215.0,
    "purchase_amount_foreign": null,
    "purchase_amount_krw": 3064500.0,
    "current_price_foreign": null,
    "current_price_krw": 9950.0,
    "market_value_foreign": null,
    "market_value_krw": 2985000.0,
    "pnl_rate": -0.02594224,
    "pnl_amount_krw": -79500.0,
    "pe": null,
    "forward_pe": null,
    "pb": null,
    "roe": null,
    "debt_ratio": null,
    "dividend_yield": null,
    "include_in_investment_base": true,
    "note": ""
  },
  {
    "row_no": 15,
    "owner": "동연",
    "broker": "KB",
    "account": "ISA",
    "country": "한국",
    "investment_currency": "원화",
    "asset_class1": "개별주식",
    "asset_class2": "AI반도체",
    "listing_currency": "KRW",
    "hedge_flag": "",
    "ticker": "005930.KS",
    "name": "삼성전자",
    "quantity": 0.0,
    "avg_price_foreign": null,
    "avg_price_krw": 208625.0,
    "purchase_amount_foreign": null,
    "purchase_amount_krw": 0.0,
    "current_price_foreign": null,
    "current_price_krw": 284000.0,
    "market_value_foreign": null,
    "market_value_krw": 0.0,
    "pnl_rate": null,
    "pnl_amount_krw": 0.0,
    "pe": null,
    "forward_pe": 5.54652,
    "pb": null,
    "roe": 0.18854,
    "debt_ratio": 5.782,
    "dividend_yield": 0.00523944,
    "include_in_investment_base": true,
    "note": ""
  },
  {
    "row_no": 16,
    "owner": "동연",
    "broker": "KB",
    "account": "ISA",
    "country": "",
    "investment_currency": "원화",
    "asset_class1": "채권",
    "asset_class2": "장기채",
    "listing_currency": "KRW",
    "hedge_flag": "",
    "ticker": "453850.KS",
    "name": "ACE 미국30년국채액티브(H)",
    "quantity": 270.0,
    "avg_price_foreign": null,
    "avg_price_krw": 7410.0,
    "purchase_amount_foreign": null,
    "purchase_amount_krw": 2000700.0,
    "current_price_foreign": null,
    "current_price_krw": 7415.0,
    "market_value_foreign": null,
    "market_value_krw": 2002050.0,
    "pnl_rate": 0.00067476,
    "pnl_amount_krw": 1350.0,
    "pe": null,
    "forward_pe": null,
    "pb": null,
    "roe": null,
    "debt_ratio": null,
    "dividend_yield": null,
    "include_in_investment_base": true,
    "note": ""
  },
  {
    "row_no": 17,
    "owner": "동연",
    "broker": "키움",
    "account": "위탁종합",
    "country": "",
    "investment_currency": "엔화",
    "asset_class1": "헷지",
    "asset_class2": "금",
    "listing_currency": "JPY",
    "hedge_flag": "",
    "ticker": "1540.T",
    "name": "MITSUBICHI JAPAN PHYSICAL GOLD ETF",
    "quantity": 31.0,
    "avg_price_foreign": 22028.4,
    "avg_price_krw": 207254.2014,
    "purchase_amount_foreign": 682880.4,
    "purchase_amount_krw": 6424880.0,
    "current_price_foreign": 22255.0,
    "current_price_krw": 209386.1675,
    "market_value_foreign": 689905.0,
    "market_value_krw": 6490971.0,
    "pnl_rate": 0.01028672,
    "pnl_amount_krw": 66091.0,
    "pe": null,
    "forward_pe": null,
    "pb": null,
    "roe": null,
    "debt_ratio": null,
    "dividend_yield": null,
    "include_in_investment_base": true,
    "note": ""
  },
  {
    "row_no": 18,
    "owner": "동연",
    "broker": "키움",
    "account": "위탁종합",
    "country": "",
    "investment_currency": "달러",
    "asset_class1": "헷지",
    "asset_class2": "금",
    "listing_currency": "JPY",
    "hedge_flag": "",
    "ticker": "1326.T",
    "name": "SPDR GOLD SHARES",
    "quantity": 4.0,
    "avg_price_foreign": 58881.6,
    "avg_price_krw": 553987.5336,
    "purchase_amount_foreign": 235526.4,
    "purchase_amount_krw": 2215950.0,
    "current_price_foreign": null,
    "current_price_krw": null,
    "market_value_foreign": null,
    "market_value_krw": null,
    "pnl_rate": null,
    "pnl_amount_krw": null,
    "pe": null,
    "forward_pe": null,
    "pb": null,
    "roe": null,
    "debt_ratio": null,
    "dividend_yield": 0.0,
    "include_in_investment_base": true,
    "note": ""
  },
  {
    "row_no": 19,
    "owner": "동연",
    "broker": "키움",
    "account": "위탁종합",
    "country": "",
    "investment_currency": "엔화",
    "asset_class1": "현금",
    "asset_class2": "엔화",
    "listing_currency": "JPY",
    "hedge_flag": "",
    "ticker": "",
    "name": "키움엔화현금",
    "quantity": null,
    "avg_price_foreign": null,
    "avg_price_krw": null,
    "purchase_amount_foreign": 186885.0,
    "purchase_amount_krw": 1758308.0,
    "current_price_foreign": null,
    "current_price_krw": null,
    "market_value_foreign": 186885.0,
    "market_value_krw": 1758308.0,
    "pnl_rate": 0.0,
    "pnl_amount_krw": 0.0,
    "pe": null,
    "forward_pe": null,
    "pb": null,
    "roe": null,
    "debt_ratio": null,
    "dividend_yield": null,
    "include_in_investment_base": true,
    "note": ""
  },
  {
    "row_no": 20,
    "owner": "동연",
    "broker": "키움",
    "account": "위탁종합",
    "country": "",
    "investment_currency": "달러",
    "asset_class1": "채권",
    "asset_class2": "초단기",
    "listing_currency": "USD",
    "hedge_flag": "",
    "ticker": "SGOV",
    "name": "iShares 0-3 Month Treasury Bond ETF",
    "quantity": 184.0,
    "avg_price_foreign": 100.5127,
    "avg_price_krw": 149631.2462,
    "purchase_amount_foreign": 18494.3368,
    "purchase_amount_krw": 27532149.0,
    "current_price_foreign": 100.51000214,
    "current_price_krw": 149627.23,
    "market_value_foreign": 18493.84039307,
    "market_value_krw": 27531410.0,
    "pnl_rate": -2.684e-05,
    "pnl_amount_krw": -739.0,
    "pe": null,
    "forward_pe": null,
    "pb": null,
    "roe": null,
    "debt_ratio": null,
    "dividend_yield": 0.0394,
    "include_in_investment_base": true,
    "note": ""
  },
  {
    "row_no": 21,
    "owner": "동연",
    "broker": "키움",
    "account": "위탁종합",
    "country": "",
    "investment_currency": "달러",
    "asset_class1": "현금",
    "asset_class2": "달러",
    "listing_currency": "USD",
    "hedge_flag": "",
    "ticker": "",
    "name": "키움달러현금",
    "quantity": null,
    "avg_price_foreign": null,
    "avg_price_krw": null,
    "purchase_amount_foreign": 7622.11,
    "purchase_amount_krw": 11346883.0,
    "current_price_foreign": null,
    "current_price_krw": null,
    "market_value_foreign": 7622.11,
    "market_value_krw": 11346883.0,
    "pnl_rate": 0.0,
    "pnl_amount_krw": 0.0,
    "pe": null,
    "forward_pe": null,
    "pb": null,
    "roe": null,
    "debt_ratio": null,
    "dividend_yield": null,
    "include_in_investment_base": true,
    "note": ""
  },
  {
    "row_no": 22,
    "owner": "동연",
    "broker": "키움",
    "account": "위탁종합",
    "country": "미국",
    "investment_currency": "달러",
    "asset_class1": "개별주식",
    "asset_class2": "IT",
    "listing_currency": "USD",
    "hedge_flag": "",
    "ticker": "AMZN",
    "name": "아마존닷컴",
    "quantity": 27.0,
    "avg_price_foreign": 201.3106,
    "avg_price_krw": 299687.064,
    "purchase_amount_foreign": 5435.3862,
    "purchase_amount_krw": 8091551.0,
    "current_price_foreign": 270.13000488,
    "current_price_krw": 402137.1357,
    "market_value_foreign": 7293.51013184,
    "market_value_krw": 10857703.0,
    "pnl_rate": 0.34185684,
    "pnl_amount_krw": 2766152.0,
    "pe": 32.3509,
    "forward_pe": 27.36677,
    "pb": 6.573626,
    "roe": 0.24285,
    "debt_ratio": 53.3,
    "dividend_yield": null,
    "include_in_investment_base": true,
    "note": ""
  },
  {
    "row_no": 23,
    "owner": "동연",
    "broker": "키움",
    "account": "위탁종합",
    "country": "미국",
    "investment_currency": "달러",
    "asset_class1": "개별주식",
    "asset_class2": "반도체장비",
    "listing_currency": "USD",
    "hedge_flag": "",
    "ticker": "AMAT",
    "name": "어플라이드 머티어리얼즈",
    "quantity": 13.0,
    "avg_price_foreign": 349.0124,
    "avg_price_krw": 519567.7796,
    "purchase_amount_foreign": 4537.1612,
    "purchase_amount_krw": 6754381.0,
    "current_price_foreign": 436.60998535,
    "current_price_krw": 649972.553,
    "market_value_foreign": 5675.92980957,
    "market_value_krw": 8449643.0,
    "pnl_rate": 0.25098703,
    "pnl_amount_krw": 1695262.0,
    "pe": 44.78051,
    "forward_pe": 30.20024,
    "pb": 15.955051,
    "roe": 0.38863,
    "debt_ratio": 33.108,
    "dividend_yield": 0.00485559,
    "include_in_investment_base": true,
    "note": "반도체 미세공정 및 패키징 장비 필수재"
  },
  {
    "row_no": 24,
    "owner": "동연",
    "broker": "키움",
    "account": "위탁종합",
    "country": "미국",
    "investment_currency": "달러",
    "asset_class1": "개별주식",
    "asset_class2": "IT",
    "listing_currency": "USD",
    "hedge_flag": "",
    "ticker": "GOOGL",
    "name": "알파벳 A",
    "quantity": 12.0,
    "avg_price_foreign": 314.4925,
    "avg_price_krw": 468178.6949,
    "purchase_amount_foreign": 3773.91,
    "purchase_amount_krw": 5618144.0,
    "current_price_foreign": 402.61999512,
    "current_price_krw": 599372.3343,
    "market_value_foreign": 4831.43994141,
    "market_value_krw": 7192468.0,
    "pnl_rate": 0.28022129,
    "pnl_amount_krw": 1574324.0,
    "pe": 30.75783,
    "forward_pe": 27.834871,
    "pb": 10.1893,
    "roe": 0.38884997,
    "debt_ratio": 20.026,
    "dividend_yield": 0.00218568,
    "include_in_investment_base": true,
    "note": ""
  },
  {
    "row_no": 25,
    "owner": "동연",
    "broker": "키움",
    "account": "위탁종합",
    "country": "미국",
    "investment_currency": "달러",
    "asset_class1": "개별주식",
    "asset_class2": "반도체장비",
    "listing_currency": "USD",
    "hedge_flag": "",
    "ticker": "TSM",
    "name": "TSMC(ADR)",
    "quantity": 10.0,
    "avg_price_foreign": 362.8433,
    "avg_price_krw": 540157.5638,
    "purchase_amount_foreign": 3628.433,
    "purchase_amount_krw": 5401576.0,
    "current_price_foreign": 399.79998779,
    "current_price_krw": 595174.2458,
    "market_value_foreign": 3997.99987793,
    "market_value_krw": 5951742.0,
    "pnl_rate": 0.10185303,
    "pnl_amount_krw": 550167.0,
    "pe": 33.996597,
    "forward_pe": 20.723423,
    "pb": 61.156242,
    "roe": 0.3621,
    "debt_ratio": 17.131,
    "dividend_yield": 0.00950475,
    "include_in_investment_base": true,
    "note": "반도체 미세공정 및 패키징 장비 필수재"
  },
  {
    "row_no": 26,
    "owner": "동연",
    "broker": "키움",
    "account": "위탁종합",
    "country": "미국",
    "investment_currency": "달러",
    "asset_class1": "개별주식",
    "asset_class2": "반도체설계",
    "listing_currency": "USD",
    "hedge_flag": "",
    "ticker": "NVDA",
    "name": "엔비디아",
    "quantity": 17.0,
    "avg_price_foreign": 186.2285,
    "avg_price_krw": 277234.6434,
    "purchase_amount_foreign": 3165.8845,
    "purchase_amount_krw": 4712989.0,
    "current_price_foreign": 225.83000183,
    "current_price_krw": 336188.6071,
    "market_value_foreign": 3839.11003113,
    "market_value_krw": 5715206.0,
    "pnl_rate": 0.21265006,
    "pnl_amount_krw": 1002217.0,
    "pe": 46.087753,
    "forward_pe": 19.865026,
    "pb": 34.893387,
    "roe": 1.01485,
    "debt_ratio": 7.255,
    "dividend_yield": 0.00017712,
    "include_in_investment_base": true,
    "note": ""
  },
  {
    "row_no": 27,
    "owner": "동연",
    "broker": "키움",
    "account": "위탁종합",
    "country": "미국",
    "investment_currency": "달러",
    "asset_class1": "개별주식",
    "asset_class2": "AI인프라",
    "listing_currency": "USD",
    "hedge_flag": "",
    "ticker": "ETN",
    "name": "이턴 코퍼레이션",
    "quantity": 0.0,
    "avg_price_foreign": 375.6694,
    "avg_price_krw": 559251.5224,
    "purchase_amount_foreign": 0.0,
    "purchase_amount_krw": 0.0,
    "current_price_foreign": 406.94000244,
    "current_price_krw": 605803.4428,
    "market_value_foreign": 0.0,
    "market_value_krw": 0.0,
    "pnl_rate": null,
    "pnl_amount_krw": 0.0,
    "pe": 39.740234,
    "forward_pe": 25.934744,
    "pb": 8.010472,
    "roe": 0.20844999,
    "debt_ratio": 110.463,
    "dividend_yield": 0.0108124,
    "include_in_investment_base": true,
    "note": "데이터센터 전력 관리 및 변압기"
  },
  {
    "row_no": 28,
    "owner": "동연",
    "broker": "키움",
    "account": "위탁종합",
    "country": "미국",
    "investment_currency": "달러",
    "asset_class1": "개별주식",
    "asset_class2": "헬스케어",
    "listing_currency": "USD",
    "hedge_flag": "",
    "ticker": "LLY",
    "name": "일라이 릴리",
    "quantity": 2.0,
    "avg_price_foreign": 912.0,
    "avg_price_krw": 1357676.16,
    "purchase_amount_foreign": 1824.0,
    "purchase_amount_krw": 2715352.0,
    "current_price_foreign": 1015.75,
    "current_price_krw": 1512126.71,
    "market_value_foreign": 2031.5,
    "market_value_krw": 3024253.0,
    "pnl_rate": 0.11376096,
    "pnl_amount_krw": 308901.0,
    "pe": 36.134827,
    "forward_pe": 22.93792,
    "pb": 29.090414,
    "roe": 1.07459,
    "debt_ratio": 139.015,
    "dividend_yield": 0.0068127,
    "include_in_investment_base": true,
    "note": ""
  },
  {
    "row_no": 29,
    "owner": "동연",
    "broker": "키움",
    "account": "위탁종합",
    "country": "미국",
    "investment_currency": "달러",
    "asset_class1": "개별주식",
    "asset_class2": "IT",
    "listing_currency": "USD",
    "hedge_flag": "",
    "ticker": "META",
    "name": "메타",
    "quantity": 0.0,
    "avg_price_foreign": 657.652,
    "avg_price_krw": 979033.3794,
    "purchase_amount_foreign": 0.0,
    "purchase_amount_krw": 0.0,
    "current_price_foreign": 616.63000488,
    "current_price_krw": 917964.7557,
    "market_value_foreign": 0.0,
    "market_value_krw": 0.0,
    "pnl_rate": null,
    "pnl_amount_krw": 0.0,
    "pe": 22.422909,
    "forward_pe": 17.040588,
    "pb": 6.4223595,
    "roe": 0.32930002,
    "debt_ratio": 35.608,
    "dividend_yield": 0.00340561,
    "include_in_investment_base": true,
    "note": ""
  },
  {
    "row_no": 30,
    "owner": "동연",
    "broker": "키움",
    "account": "위탁종합",
    "country": "",
    "investment_currency": "달러",
    "asset_class1": "지수",
    "asset_class2": "S&P500",
    "listing_currency": "USD",
    "hedge_flag": "",
    "ticker": "VOO",
    "name": "S&P 500 뱅가드 ETF",
    "quantity": 0.0,
    "avg_price_foreign": 624.7008,
    "avg_price_krw": 929979.5869,
    "purchase_amount_foreign": 0.0,
    "purchase_amount_krw": 0.0,
    "current_price_foreign": 682.40997314,
    "current_price_krw": 1015890.0788,
    "market_value_foreign": 0.0,
    "market_value_krw": 0.0,
    "pnl_rate": null,
    "pnl_amount_krw": 0.0,
    "pe": null,
    "forward_pe": null,
    "pb": null,
    "roe": null,
    "debt_ratio": null,
    "dividend_yield": 0.0108,
    "include_in_investment_base": true,
    "note": ""
  },
  {
    "row_no": 31,
    "owner": "동연",
    "broker": "키움",
    "account": "위탁종합",
    "country": "미국",
    "investment_currency": "달러",
    "asset_class1": "개별주식",
    "asset_class2": "AI인프라",
    "listing_currency": "USD",
    "hedge_flag": "",
    "ticker": "VRT",
    "name": "버티브 홀딩스",
    "quantity": 0.0,
    "avg_price_foreign": 243.0095,
    "avg_price_krw": 361763.3825,
    "purchase_amount_foreign": 0.0,
    "purchase_amount_krw": 0.0,
    "current_price_foreign": 369.98999023,
    "current_price_krw": 550796.6987,
    "market_value_foreign": 0.0,
    "market_value_krw": 0.0,
    "pnl_rate": null,
    "pnl_amount_krw": 0.0,
    "pe": 93.19647,
    "forward_pe": 42.30188,
    "pb": 35.910896,
    "roe": 0.45097,
    "debt_ratio": 76.913,
    "dividend_yield": 0.00067569,
    "include_in_investment_base": true,
    "note": "데이터센터 액체 냉각"
  },
  {
    "row_no": 32,
    "owner": "동연",
    "broker": "키움",
    "account": "위탁종합",
    "country": "미국",
    "investment_currency": "달러",
    "asset_class1": "개별주식",
    "asset_class2": "AI인프라",
    "listing_currency": "USD",
    "hedge_flag": "",
    "ticker": "VST",
    "name": "비스트라",
    "quantity": 0.0,
    "avg_price_foreign": null,
    "avg_price_krw": null,
    "purchase_amount_foreign": null,
    "purchase_amount_krw": null,
    "current_price_foreign": 142.61000061,
    "current_price_krw": 212300.6557,
    "market_value_foreign": 0.0,
    "market_value_krw": 0.0,
    "pnl_rate": null,
    "pnl_amount_krw": null,
    "pe": 23.847826,
    "forward_pe": 12.635046,
    "pb": 18.39417,
    "roe": 0.42898,
    "debt_ratio": 355.187,
    "dividend_yield": 0.00645116,
    "include_in_investment_base": true,
    "note": "원자력 발전 기반 유틸리티"
  },
  {
    "row_no": 33,
    "owner": "동연",
    "broker": "키움",
    "account": "위탁종합",
    "country": "",
    "investment_currency": "달러",
    "asset_class1": "채권",
    "asset_class2": "장기채",
    "listing_currency": "USD",
    "hedge_flag": "",
    "ticker": "TLT",
    "name": "미국 +20년 장기 국채",
    "quantity": 21.0,
    "avg_price_foreign": 85.6859,
    "avg_price_krw": 127558.8856,
    "purchase_amount_foreign": 1799.4039,
    "purchase_amount_krw": 2678737.0,
    "current_price_foreign": 84.80000305,
    "current_price_krw": 126240.0685,
    "market_value_foreign": 1780.80006409,
    "market_value_krw": 2651041.0,
    "pnl_rate": -0.01033889,
    "pnl_amount_krw": -27695.0,
    "pe": null,
    "forward_pe": null,
    "pb": null,
    "roe": null,
    "debt_ratio": null,
    "dividend_yield": 0.0457,
    "include_in_investment_base": true,
    "note": ""
  },
  {
    "row_no": 34,
    "owner": "동연",
    "broker": "키움",
    "account": "위탁종합",
    "country": "",
    "investment_currency": "원화",
    "asset_class1": "현금",
    "asset_class2": "원화",
    "listing_currency": "KRW",
    "hedge_flag": "",
    "ticker": "",
    "name": "키움원화현금",
    "quantity": null,
    "avg_price_foreign": null,
    "avg_price_krw": null,
    "purchase_amount_foreign": null,
    "purchase_amount_krw": 100008.0,
    "current_price_foreign": null,
    "current_price_krw": null,
    "market_value_foreign": null,
    "market_value_krw": 100008.0,
    "pnl_rate": 0.0,
    "pnl_amount_krw": 0.0,
    "pe": null,
    "forward_pe": null,
    "pb": null,
    "roe": null,
    "debt_ratio": null,
    "dividend_yield": null,
    "include_in_investment_base": true,
    "note": ""
  },
  {
    "row_no": 35,
    "owner": "완서",
    "broker": "키움",
    "account": "ISA",
    "country": "",
    "investment_currency": "원화",
    "asset_class1": "현금",
    "asset_class2": "원화",
    "listing_currency": "KRW",
    "hedge_flag": "",
    "ticker": "",
    "name": "키움원화현금",
    "quantity": null,
    "avg_price_foreign": null,
    "avg_price_krw": null,
    "purchase_amount_foreign": null,
    "purchase_amount_krw": 11379307.0,
    "current_price_foreign": null,
    "current_price_krw": null,
    "market_value_foreign": null,
    "market_value_krw": 11379307.0,
    "pnl_rate": 0.0,
    "pnl_amount_krw": 0.0,
    "pe": null,
    "forward_pe": null,
    "pb": null,
    "roe": null,
    "debt_ratio": null,
    "dividend_yield": null,
    "include_in_investment_base": true,
    "note": ""
  },
  {
    "row_no": 36,
    "owner": "완서",
    "broker": "키움",
    "account": "ISA",
    "country": "",
    "investment_currency": "원화",
    "asset_class1": "지수",
    "asset_class2": "S&P500",
    "listing_currency": "KRW",
    "hedge_flag": "O",
    "ticker": "453330.KS",
    "name": "RISE 미국 S&P500(H)",
    "quantity": 627.0,
    "avg_price_foreign": null,
    "avg_price_krw": 16334.0,
    "purchase_amount_foreign": null,
    "purchase_amount_krw": 10241418.0,
    "current_price_foreign": null,
    "current_price_krw": 17580.0,
    "market_value_foreign": null,
    "market_value_krw": 11022660.0,
    "pnl_rate": 0.0762826,
    "pnl_amount_krw": 781242.0,
    "pe": null,
    "forward_pe": null,
    "pb": null,
    "roe": null,
    "debt_ratio": null,
    "dividend_yield": null,
    "include_in_investment_base": true,
    "note": ""
  },
  {
    "row_no": 37,
    "owner": "완서",
    "broker": "키움",
    "account": "ISA",
    "country": "한국",
    "investment_currency": "원화",
    "asset_class1": "개별주식",
    "asset_class2": "AI반도체",
    "listing_currency": "KRW",
    "hedge_flag": "",
    "ticker": "005930.KS",
    "name": "삼성전자",
    "quantity": 13.0,
    "avg_price_foreign": null,
    "avg_price_krw": 215700.0,
    "purchase_amount_foreign": null,
    "purchase_amount_krw": 2804100.0,
    "current_price_foreign": null,
    "current_price_krw": 284000.0,
    "market_value_foreign": null,
    "market_value_krw": 3692000.0,
    "pnl_rate": 0.31664349,
    "pnl_amount_krw": 887900.0,
    "pe": null,
    "forward_pe": 5.54652,
    "pb": null,
    "roe": 0.18854,
    "debt_ratio": 5.782,
    "dividend_yield": 0.00523944,
    "include_in_investment_base": true,
    "note": ""
  },
  {
    "row_no": 38,
    "owner": "완서",
    "broker": "키움",
    "account": "ISA",
    "country": "",
    "investment_currency": "달러",
    "asset_class1": "지수",
    "asset_class2": "S&P500동일가중",
    "listing_currency": "KRW",
    "hedge_flag": "",
    "ticker": "488500.KS",
    "name": "TIGER 미국S&P500동일가중",
    "quantity": 49.0,
    "avg_price_foreign": null,
    "avg_price_krw": 12210.0,
    "purchase_amount_foreign": null,
    "purchase_amount_krw": 598290.0,
    "current_price_foreign": null,
    "current_price_krw": 12850.0,
    "market_value_foreign": null,
    "market_value_krw": 629650.0,
    "pnl_rate": 0.05241605,
    "pnl_amount_krw": 31360.0,
    "pe": null,
    "forward_pe": null,
    "pb": null,
    "roe": null,
    "debt_ratio": null,
    "dividend_yield": null,
    "include_in_investment_base": true,
    "note": ""
  },
  {
    "row_no": 39,
    "owner": "완서",
    "broker": "키움",
    "account": "ISA",
    "country": "",
    "investment_currency": "달러",
    "asset_class1": "채권",
    "asset_class2": "장기채",
    "listing_currency": "KRW",
    "hedge_flag": "",
    "ticker": "476760.KS",
    "name": "ACE 미국30년국채액티브",
    "quantity": 0.0,
    "avg_price_foreign": null,
    "avg_price_krw": null,
    "purchase_amount_foreign": null,
    "purchase_amount_krw": null,
    "current_price_foreign": null,
    "current_price_krw": 9950.0,
    "market_value_foreign": null,
    "market_value_krw": 0.0,
    "pnl_rate": null,
    "pnl_amount_krw": null,
    "pe": null,
    "forward_pe": null,
    "pb": null,
    "roe": null,
    "debt_ratio": null,
    "dividend_yield": null,
    "include_in_investment_base": true,
    "note": ""
  },
  {
    "row_no": 40,
    "owner": "완서",
    "broker": "키움",
    "account": "ISA",
    "country": "",
    "investment_currency": "원화",
    "asset_class1": "채권",
    "asset_class2": "장기채",
    "listing_currency": "KRW",
    "hedge_flag": "",
    "ticker": "453850.KS",
    "name": "ACE 미국30년국채액티브(H)",
    "quantity": 0.0,
    "avg_price_foreign": null,
    "avg_price_krw": null,
    "purchase_amount_foreign": null,
    "purchase_amount_krw": null,
    "current_price_foreign": null,
    "current_price_krw": 7415.0,
    "market_value_foreign": null,
    "market_value_krw": 0.0,
    "pnl_rate": null,
    "pnl_amount_krw": null,
    "pe": null,
    "forward_pe": null,
    "pb": null,
    "roe": null,
    "debt_ratio": null,
    "dividend_yield": null,
    "include_in_investment_base": true,
    "note": ""
  },
  {
    "row_no": 41,
    "owner": "완서",
    "broker": "",
    "account": "주택청약",
    "country": "",
    "investment_currency": "원화",
    "asset_class1": "예금",
    "asset_class2": "장기예금",
    "listing_currency": "KRW",
    "hedge_flag": "",
    "ticker": "",
    "name": "주택청약저축",
    "quantity": null,
    "avg_price_foreign": null,
    "avg_price_krw": null,
    "purchase_amount_foreign": null,
    "purchase_amount_krw": 12200000.0,
    "current_price_foreign": null,
    "current_price_krw": null,
    "market_value_foreign": null,
    "market_value_krw": 12200000.0,
    "pnl_rate": 0.0,
    "pnl_amount_krw": 0.0,
    "pe": null,
    "forward_pe": null,
    "pb": null,
    "roe": null,
    "debt_ratio": null,
    "dividend_yield": null,
    "include_in_investment_base": false,
    "note": ""
  },
  {
    "row_no": 42,
    "owner": "완서",
    "broker": "",
    "account": "",
    "country": "",
    "investment_currency": "원화",
    "asset_class1": "예금",
    "asset_class2": "장기예금",
    "listing_currency": "KRW",
    "hedge_flag": "",
    "ticker": "",
    "name": "청년도약계좌(월60만원)",
    "quantity": null,
    "avg_price_foreign": null,
    "avg_price_krw": null,
    "purchase_amount_foreign": null,
    "purchase_amount_krw": 14400000.0,
    "current_price_foreign": null,
    "current_price_krw": null,
    "market_value_foreign": null,
    "market_value_krw": 14400000.0,
    "pnl_rate": 0.0,
    "pnl_amount_krw": 0.0,
    "pe": null,
    "forward_pe": null,
    "pb": null,
    "roe": null,
    "debt_ratio": null,
    "dividend_yield": null,
    "include_in_investment_base": false,
    "note": "(5년만기:29년5월)4월 반영"
  }
]